margin_estimator/__init__.py
margin_estimator/margin.py
margin_estimator/models.py
margin_estimator/py.typed
margin_estimator-0.3.dist-info/METADATA
margin_estimator-0.3.dist-info/WHEEL
margin_estimator-0.3.dist-info/licenses/LICENSE
margin_estimator-0.3.dist-info/RECORD
