Metadata-Version: 2.4
Name: margin-estimator
Version: 0.3
Summary: Calculate estimated margin requirements for equities options, based on CBOE margining.
Project-URL: Homepage, https://github.com/tastyware/margin-estimator
Author-email: Graeme Holliday <graeme.holliday@pm.me>
License: MIT License
License-File: LICENSE
Requires-Python: >=3.11
Requires-Dist: pydantic>=2.9.2
